db_pools.py
db_utils.py
decorator_utils.py
file_utils.py
log_utils.py
main_u-0.2.9.dist-info/METADATA
main_u-0.2.9.dist-info/WHEEL
main_u-0.2.9.dist-info/top_level.txt
main_u-0.2.9.dist-info/RECORD
