Metadata-Version: 2.1
Name: main_u
Version: 0.2.9
Summary: some moudle:['file_utils', 'db_utils', 'log_utils', 'decorator_utils']
Author: linshenghua
Author-email: 780141734@qq.com
Classifier: Programming Language :: Python :: 3.9
Classifier: License :: OSI Approved :: MIT License
Classifier: Operating System :: OS Independent
Requires-Dist: pymysql
Requires-Dist: sshtunnel ==0.4.0
Requires-Dist: PyYAML ==6.0.1
Requires-Dist: xlrd ==1.2.0
Requires-Dist: xlwt ==1.3.0
Requires-Dist: dbutils
Requires-Dist: requests
Requires-Dist: beautifulsoup4
Requires-Dist: pandas
Requires-Dist: openpyxl
